pixelsparser/Pixel.py
pixelsparser/__init__.py
pixelsparser/utils.py
pixelsparser-2.0.1.dist-info/LICENSE
pixelsparser-2.0.1.dist-info/METADATA
pixelsparser-2.0.1.dist-info/WHEEL
pixelsparser-2.0.1.dist-info/top_level.txt
pixelsparser-2.0.1.dist-info/RECORD
