Metadata-Version: 2.1
Name: pixelsparser
Version: 2.0.1
Summary: A python library that allows users to import their Pixels JSON data and use it in their python scripts.
Author-email: Constantinos Psomadakis <business@tinosps.com>
Project-URL: Homepage, https://github.com/pTinosq/pixelsparser/
Project-URL: Bug Tracker, https://github.com/pTinosq/pixelsparser/issues
Classifier: Programming Language :: Python :: 3
Classifier: License :: OSI Approved :: GNU General Public License v3 (GPLv3)
Classifier: Operating System :: OS Independent
Requires-Python: >=3.7
License-File: LICENSE
